{
  "help" : "help [plugin] : 显示[插件]的使用方法",
  "echo": "echo <内容> : 回复<内容>",
  "reply": "reply : (非命令)自动回复",
  "latex": "latex <公式> : 以图片形式回复latex<公式>",
  "setu": "setu [drawings/hentai/neutral/porn/sexy] : 随机发送setu，默认库为drawings",
  "百度": "百度 <搜索词> [显示字数] : 回复百度搜索<搜索词>的内容",
  "点歌": "点歌 <搜索词> [分享条数i] : 分享qq音乐搜索<搜索词>的第i个结果",
  "计时": "计时 <倒计时> : 设置一个倒计时",
  "闹钟": "闹钟 <闹钟名> <时间> : 设定一个闹钟",
  "说话": "说话 <内容> [参数] : 发送语音<内容>，参数:voiceId/speed/volume/audioType",
  "对话": "对话 <内容> [参数] : 智能回复语音<内容>，参数同\"说话\"",
  "防撤回": "防撤回 : (非命令)回复被撤回的内容"
}